html2text_rs-0.2.5.dist-info/METADATA
html2text_rs-0.2.5.dist-info/WHEEL
html2text_rs-0.2.5.dist-info/licenses/LICENSE
html2text_rs/__init__.py
html2text_rs/html2text_rs.cpython-313t-arm-linux-gnueabihf.so
html2text_rs/html2text_rs.pyi
html2text_rs/py.typed
html2text_rs-0.2.5.dist-info/RECORD
